pypetkit/__init__.py
pypetkit/const.py
pypetkit/device.py
pypetkit/history.py
pypetkit/pypetkit.py
pypetkit/schedule.py
pypetkit-0.0.4.dist-info/LICENSE
pypetkit-0.0.4.dist-info/METADATA
pypetkit-0.0.4.dist-info/WHEEL
pypetkit-0.0.4.dist-info/top_level.txt
pypetkit-0.0.4.dist-info/RECORD
