Metadata-Version: 2.1
Name: pypetkit
Version: 0.0.4
Summary: PetKit python integration library
Home-page: https://github.com/CrazYoshi/pypetkit
Author: CrazYoshi
Author-email: crazyoshi1186@gmail.com
License: UNKNOWN
Platform: UNKNOWN
Classifier: Programming Language :: Python :: 3.3
Classifier: Programming Language :: Python :: 3.4
Classifier: Programming Language :: Python :: 3.5
Classifier: Programming Language :: Python :: 3.6
Classifier: License :: OSI Approved :: MIT License
Classifier: Operating System :: OS Independent
